{
  "generated_utc": "2026-03-07T08:13:21+00:00",
  "system_id": "heart_did_method_conformance_suite",
  "pillar": "heart",
  "overall_status": "PASS",
  "checks": [
    {
      "name": "did_verifier_tokens",
      "status": "PASS",
      "detail": "missing_tokens=0"
    },
    {
      "name": "governance_status",
      "status": "PASS",
      "detail": "status=PASS"
    }
  ],
  "metrics": {
    "required_token_count": 3,
    "missing_token_count": 0
  },
  "repo_targets_touched": [
    "docs/heart-track-governance-latest.json",
    "freed_id_did_signature_verifier.py"
  ],
  "next_action": "Extend DID conformance vectors as GOV-004 verification expands.",
  "effective_success": true
}
