{
  "generated_utc": "2026-03-07T08:33:18+00:00",
  "system_id": "mind_theory_signal_refresh_semanticscholar",
  "pillar": "mind",
  "overall_status": "PASS",
  "checks": [
    {
      "name": "live_fallback",
      "status": "PASS",
      "detail": "semanticscholar fallback used (HTTP Error 429: )"
    }
  ],
  "metrics": {
    "offline_only": false,
    "record_count": 3
  },
  "repo_targets_touched": [
    "docs/comparative-validation-grid-v1.md"
  ],
  "next_action": "Merge Semantic Scholar and Crossref records.",
  "effective_success": true,
  "records": [
    {
      "source_id": "semanticscholar",
      "record_id": "ec21b719d7713e1ed14c4ca78f06ea8609d44bc4",
      "signal_type": "theory_context",
      "title": "De Sitter vacua in string theory",
      "published_at": "2003-01-29",
      "source_url": "https://www.semanticscholar.org/paper/ec21b719d7713e1ed14c4ca78f06ea8609d44bc4",
      "summary": "Semantic Scholar signal for string theory.",
      "metrics": {
        "query_id": "mind-string-theory",
        "citation_count": 3373,
        "year": 2003
      },
      "tags": [
        "mind",
        "semanticscholar"
      ],
      "repo_targets": [
        "docs/comparative-validation-grid-v1.md",
        "docs/trinity-public-research-brief-2026-03-06.md"
      ]
    },
    {
      "source_id": "semanticscholar",
      "record_id": "557bc7143ef3e00b011cefc7be683af8579b42e1",
      "signal_type": "theory_context",
      "title": "String theory and noncommutative geometry",
      "published_at": "1999-08-20",
      "source_url": "https://www.semanticscholar.org/paper/557bc7143ef3e00b011cefc7be683af8579b42e1",
      "summary": "Semantic Scholar signal for string theory.",
      "metrics": {
        "query_id": "mind-string-theory",
        "citation_count": 4479,
        "year": 1999
      },
      "tags": [
        "mind",
        "semanticscholar"
      ],
      "repo_targets": [
        "docs/comparative-validation-grid-v1.md",
        "docs/trinity-public-research-brief-2026-03-06.md"
      ]
    },
    {
      "source_id": "semanticscholar",
      "record_id": "5c128f92f1a37bf242e0c139c045502b990151fb",
      "signal_type": "theory_context",
      "title": "Gauge Theory Correlators from Non-Critical String Theory",
      "published_at": "1998-02-16",
      "source_url": "https://www.semanticscholar.org/paper/5c128f92f1a37bf242e0c139c045502b990151fb",
      "summary": "Semantic Scholar signal for string theory.",
      "metrics": {
        "query_id": "mind-string-theory",
        "citation_count": 10546,
        "year": 1998
      },
      "tags": [
        "mind",
        "semanticscholar"
      ],
      "repo_targets": [
        "docs/comparative-validation-grid-v1.md",
        "docs/trinity-public-research-brief-2026-03-06.md"
      ]
    }
  ],
  "source_runs": [
    {
      "source_id": "semanticscholar",
      "mode": "fallback_cache",
      "record_count": 3,
      "status": "PASS"
    }
  ]
}
