{
  "generated_utc": "2026-03-06T02:30:41.363286+00:00",
  "engine": "trinity-energy-bank-system",
  "inputs": {
    "reserve_growth": 1.0,
    "reserve_cap_multiplier": 27.921484,
    "auto_max_cap": true,
    "cap_ceiling": 100.0,
    "projection_sessions": 10,
    "regenerated_tokens": 17176.644196,
    "regenerated_credits": 17.176644,
    "net_usable_energy": 89.6975,
    "cache_reclaimed_tokens": 733.7,
    "cache_reclaimed_credits": 0.7337,
    "cache_reclaimed_energy_units": 0.7337,
    "reserve_tokens_consumed": 8081.758973,
    "reserve_credits_consumed": 12.0,
    "reserve_energy_consumed": 8.081759
  },
  "outputs": {
    "post_spend_tokens": 0.0,
    "post_spend_credits": 24.62416,
    "post_spend_energy_units": 2955.274133,
    "reserve_cap_tokens": 496607.387825,
    "reserve_cap_credits": 3065.821579,
    "reserve_cap_energy_units": 82741.294125,
    "reserve_tokens": 17910.344196,
    "reserve_credits": 42.534504,
    "reserve_energy_units": 3045.705333,
    "projected_sessions": [
      {
        "session": 1,
        "planned_tokens": 10200,
        "planned_credits": 10.2,
        "token_coverage_ratio": 1.0,
        "covered_tokens": 10200,
        "covered_credits": 10.2,
        "uncovered_tokens": 0.0,
        "uncovered_credits": 0.0,
        "token_surplus_after_session": 7710.344196,
        "credit_surplus_after_session": 32.334504
      },
      {
        "session": 2,
        "planned_tokens": 11400,
        "planned_credits": 11.4,
        "token_coverage_ratio": 0.676346,
        "covered_tokens": 7710.344196,
        "covered_credits": 11.4,
        "uncovered_tokens": 3689.655804,
        "uncovered_credits": 0.0,
        "token_surplus_after_session": 0.0,
        "credit_surplus_after_session": 20.934504
      },
      {
        "session": 3,
        "planned_tokens": 12600,
        "planned_credits": 12.6,
        "token_coverage_ratio": 0.0,
        "covered_tokens": 0.0,
        "covered_credits": 12.6,
        "uncovered_tokens": 12600.0,
        "uncovered_credits": 0.0,
        "token_surplus_after_session": 0.0,
        "credit_surplus_after_session": 8.334504
      },
      {
        "session": 4,
        "planned_tokens": 13800,
        "planned_credits": 13.8,
        "token_coverage_ratio": 0.0,
        "covered_tokens": 0.0,
        "covered_credits": 8.334504,
        "uncovered_tokens": 13800.0,
        "uncovered_credits": 5.465496,
        "token_surplus_after_session": 0.0,
        "credit_surplus_after_session": 0.0
      },
      {
        "session": 5,
        "planned_tokens": 15000,
        "planned_credits": 15.0,
        "token_coverage_ratio": 0.0,
        "covered_tokens": 0.0,
        "covered_credits": 0.0,
        "uncovered_tokens": 15000.0,
        "uncovered_credits": 15.0,
        "token_surplus_after_session": 0.0,
        "credit_surplus_after_session": 0.0
      },
      {
        "session": 6,
        "planned_tokens": 16200,
        "planned_credits": 16.2,
        "token_coverage_ratio": 0.0,
        "covered_tokens": 0.0,
        "covered_credits": 0.0,
        "uncovered_tokens": 16200.0,
        "uncovered_credits": 16.2,
        "token_surplus_after_session": 0.0,
        "credit_surplus_after_session": 0.0
      },
      {
        "session": 7,
        "planned_tokens": 17400,
        "planned_credits": 17.4,
        "token_coverage_ratio": 0.0,
        "covered_tokens": 0.0,
        "covered_credits": 0.0,
        "uncovered_tokens": 17400.0,
        "uncovered_credits": 17.4,
        "token_surplus_after_session": 0.0,
        "credit_surplus_after_session": 0.0
      },
      {
        "session": 8,
        "planned_tokens": 18600,
        "planned_credits": 18.6,
        "token_coverage_ratio": 0.0,
        "covered_tokens": 0.0,
        "covered_credits": 0.0,
        "uncovered_tokens": 18600.0,
        "uncovered_credits": 18.6,
        "token_surplus_after_session": 0.0,
        "credit_surplus_after_session": 0.0
      },
      {
        "session": 9,
        "planned_tokens": 19800,
        "planned_credits": 19.8,
        "token_coverage_ratio": 0.0,
        "covered_tokens": 0.0,
        "covered_credits": 0.0,
        "uncovered_tokens": 19800.0,
        "uncovered_credits": 19.8,
        "token_surplus_after_session": 0.0,
        "credit_surplus_after_session": 0.0
      },
      {
        "session": 10,
        "planned_tokens": 21000,
        "planned_credits": 21.0,
        "token_coverage_ratio": 0.0,
        "covered_tokens": 0.0,
        "covered_credits": 0.0,
        "uncovered_tokens": 21000.0,
        "uncovered_credits": 21.0,
        "token_surplus_after_session": 0.0,
        "credit_surplus_after_session": 0.0
      }
    ],
    "projection_summary": {
      "sessions": 10,
      "planned_tokens": 156000.0,
      "covered_tokens": 17910.344196,
      "uncovered_tokens": 138089.655804,
      "planned_credits": 156.0,
      "covered_credits": 42.534504,
      "uncovered_credits": 113.465496
    }
  }
}
